data_lake_vqd_utils/DatabaseInserter.py
data_lake_vqd_utils/S3FileHandler.py
data_lake_vqd_utils/__init__.py
datalake_vqd_utils-0.0.21.dist-info/LICENSE
datalake_vqd_utils-0.0.21.dist-info/METADATA
datalake_vqd_utils-0.0.21.dist-info/WHEEL
datalake_vqd_utils-0.0.21.dist-info/top_level.txt
datalake_vqd_utils-0.0.21.dist-info/RECORD
