Metadata-Version: 2.1
Name: datalake-vqd-utils
Version: 0.0.21
Summary: Package containing tools for cloud-based data lakes
Home-page: https://github.com/pypa/sampleproject
Author: Casper van Houten
Author-email: casper.vanhouten@viqtordavis.com
License: UNKNOWN
Platform: UNKNOWN
Classifier: Programming Language :: Python :: 3
Classifier: License :: OSI Approved :: MIT License
Classifier: Operating System :: OS Independent
Requires-Python: >=3.6
Requires-Dist: boto3 (>=1.9.222)
Requires-Dist: sqlalchemy (>=1.3.13)
Requires-Dist: pymysql (>=0.9.3)
Requires-Dist: pandas (>=0.23.4)
